odoo/addons/report_paperformat_company_dependent/README.rst
odoo/addons/report_paperformat_company_dependent/__init__.py
odoo/addons/report_paperformat_company_dependent/__manifest__.py
odoo/addons/report_paperformat_company_dependent/hooks.py
odoo/addons/report_paperformat_company_dependent/i18n/it.po
odoo/addons/report_paperformat_company_dependent/i18n/report_paperformat_company_dependent.pot
odoo/addons/report_paperformat_company_dependent/models/__init__.py
odoo/addons/report_paperformat_company_dependent/models/ir_actions_report.py
odoo/addons/report_paperformat_company_dependent/readme/CONTEXT.rst
odoo/addons/report_paperformat_company_dependent/readme/CONTRIBUTORS.rst
odoo/addons/report_paperformat_company_dependent/readme/DESCRIPTION.rst
odoo/addons/report_paperformat_company_dependent/static/description/icon.png
odoo/addons/report_paperformat_company_dependent/static/description/index.html
odoo_addon_report_paperformat_company_dependent-16.0.1.0.0.4.dist-info/METADATA
odoo_addon_report_paperformat_company_dependent-16.0.1.0.0.4.dist-info/WHEEL
odoo_addon_report_paperformat_company_dependent-16.0.1.0.0.4.dist-info/top_level.txt
odoo_addon_report_paperformat_company_dependent-16.0.1.0.0.4.dist-info/RECORD
